README.rst
setup.py
pycachu/__init__.py
pycachu.egg-info/PKG-INFO
pycachu.egg-info/SOURCES.txt
pycachu.egg-info/dependency_links.txt
pycachu.egg-info/top_level.txt