Metadata-Version: 1.1
Name: pycachu
Version: 0.1.0
Summary: A basic Python package to store files in a LRU cache.
Home-page: https://github.com/Xowap/pycachu
Author: Rémy Sanchez
Author-email: remy.sanchez@activkonnect.com
License: WTFPL
Platform: UNKNOWN
Classifier: Environment :: Web Environment
Classifier: Intended Audience :: Developers
Classifier: License :: Other/Proprietary License
Classifier: Programming Language :: Python
Classifier: Programming Language :: Python :: 2
Classifier: Programming Language :: Python :: 2.7
Classifier: Programming Language :: Python :: 3
Classifier: Programming Language :: Python :: 3.0
Classifier: Programming Language :: Python :: 3.1
Classifier: Programming Language :: Python :: 3.2
Classifier: Programming Language :: Python :: 3.3
Classifier: Programming Language :: Python :: 3.4
